chatbot_analysis/__init__.py
chatbot_analysis/models.py
chatbot_analysis/package.py
chatbot_analysis-0.9.dist-info/METADATA
chatbot_analysis-0.9.dist-info/WHEEL
chatbot_analysis-0.9.dist-info/entry_points.txt
chatbot_analysis-0.9.dist-info/top_level.txt
chatbot_analysis-0.9.dist-info/RECORD
