Metadata-Version: 2.1
Name: chatbot-analysis
Version: 0.9
Requires-Python: >=3.7
Requires-Dist: torch>=2.0.0
Requires-Dist: transformers>=4.10.0
Requires-Dist: pandas>=1.5.3
Requires-Dist: tabulate>=0.9.0
